{"version":1,"resource":"file:///home/dplepler/Documents/Projects/AtOSx64/AtOSx64/linker.ld","entries":[{"id":"SJTZ.ld","timestamp":1649430354021},{"id":"ceBi.ld","timestamp":1649431086490},{"id":"rrBt.ld","source":"undoRedo.source","timestamp":1649431093802},{"id":"ZEpm.ld","timestamp":1649431297676},{"id":"qzeW.ld","timestamp":1649432530694},{"id":"XNsn.ld","timestamp":1649432607767},{"id":"ACpK.ld","timestamp":1649432662799},{"id":"axC3.ld","timestamp":1649432719828},{"id":"Rac9.ld","timestamp":1649432731104},{"id":"6HSS.ld","timestamp":1649432743752},{"id":"PCtq.ld","timestamp":1649432754488},{"id":"bsx6.ld","timestamp":1649433994928},{"id":"eq08.ld","timestamp":1649434101052},{"id":"yG4t.ld","timestamp":1649434474367},{"id":"VIA9.ld","timestamp":1649436090867},{"id":"NBmv.ld","timestamp":1649436186684},{"id":"AqaT.ld","timestamp":1649436200984},{"id":"cjaT.ld","timestamp":1649436308688},{"id":"CQcZ.ld","timestamp":1649443241915},{"id":"nKz5.ld","timestamp":1649443260943},{"id":"85pF.ld","source":"undoRedo.source","timestamp":1649444166161},{"id":"3gs4.ld","timestamp":1649444247926},{"id":"BpSB.ld","source":"undoRedo.source","timestamp":1649444891618},{"id":"IySj.ld","timestamp":1649444904114},{"id":"8wii.ld","timestamp":1649444924811},{"id":"aRUz.ld","timestamp":1649445139757},{"id":"eOmp.ld","timestamp":1649447925837},{"id":"CiBD.ld","timestamp":1649447941245},{"id":"OI5O.ld","timestamp":1649447959809},{"id":"0lhe.ld","timestamp":1649448012514},{"id":"K7MR.ld","timestamp":1649448026874},{"id":"iIXO.ld","timestamp":1649448064698},{"id":"ZjfO.ld","timestamp":1649448088767}]}